pyreproj/__init__.py
pyreproj/exception/__init__.py
pyreproj-3.0.0.dist-info/LICENSE
pyreproj-3.0.0.dist-info/METADATA
pyreproj-3.0.0.dist-info/WHEEL
pyreproj-3.0.0.dist-info/top_level.txt
pyreproj-3.0.0.dist-info/RECORD
