Metadata-Version: 2.1
Name: pyreproj
Version: 3.0.0
Summary: Python Reprojector
Home-page: https://gitlab.com/geo-bl-ch/python-reprojector
Author: Karsten Deininger
Author-email: karsten.deininger@bl.ch
License: BSD
Keywords: web proj coordinate transformation
Classifier: Development Status :: 5 - Production/Stable
Classifier: Programming Language :: Python :: 3.8
Classifier: Programming Language :: Python :: 3.9
Classifier: Programming Language :: Python :: 3.10
Classifier: Programming Language :: Python :: 3.11
Classifier: Topic :: Scientific/Engineering :: GIS
Classifier: Topic :: Utilities
Classifier: Natural Language :: English
Classifier: License :: OSI Approved :: BSD License
Classifier: Intended Audience :: Developers
Classifier: Operating System :: OS Independent
License-File: LICENSE
Requires-Dist: pyproj >=2.2.0
Requires-Dist: shapely
Requires-Dist: requests
